transpile_run_validate
