Metadata-Version: 2.1
Name: clickzetta-transpile-run-validate
Version: 0.0.1.15
Summary: clickzetta transpile,run,validate tool
Home-page: https://www.yunqi.tech/
Author: mocun
Author-email: hanmiao.li@clickzetta.com
Platform: Posix; MacOS X;
Requires-Python: >=3.7
Provides-Extra: all
License-File: LICENSE
